pygsk/__init__.py
pygsk/core.py
pygsk/plot.py
pygsk/runtests.py
pygsk/simulator.py
pygsk/thresholds.py
pygsk/cli/__init__.py
pygsk/cli/__main__.py
pygsk/cli/main.py
pygsk/cli/parser.py
pygsk/cli/sk_cli.py
pygsk/cli/sk_renorm_cli.py
pygsk/cli/sk_thresholds_cli.py
pygsk/cli/sk_thresholds_sweep_cli.py
pygsk-2.2.3.dist-info/licenses/LICENSE
pygsk-2.2.3.dist-info/METADATA
pygsk-2.2.3.dist-info/WHEEL
pygsk-2.2.3.dist-info/entry_points.txt
pygsk-2.2.3.dist-info/top_level.txt
pygsk-2.2.3.dist-info/RECORD
