Metadata-Version: 2.4
Name: pygsk
Version: 2.2.3
Summary: Generalized Spectral Kurtosis Toolkit
Author: Gelu M. Nita
License: MIT
Project-URL: Homepage, https://github.com/SUNCAST-org/pygsk
Project-URL: Source, https://github.com/SUNCAST-org/pygsk
Project-URL: Bug Tracker, https://github.com/SUNCAST-org/pygsk/issues
Project-URL: Changelog, https://github.com/SUNCAST-org/pygsk/releases
Project-URL: DOI, https://doi.org/10.5281/zenodo.17336193
Keywords: spectral-kurtosis,radio-astronomy,signal-processing,statistics,solar-physics
Classifier: Development Status :: 4 - Beta
Classifier: Intended Audience :: Science/Research
Classifier: License :: OSI Approved :: MIT License
Classifier: Programming Language :: Python
Classifier: Programming Language :: Python :: 3
Classifier: Programming Language :: Python :: 3 :: Only
Classifier: Programming Language :: Python :: 3.9
Classifier: Programming Language :: Python :: 3.10
Classifier: Programming Language :: Python :: 3.11
Classifier: Programming Language :: Python :: 3.12
Classifier: Topic :: Scientific/Engineering
Classifier: Topic :: Scientific/Engineering :: Information Analysis
Classifier: Topic :: Scientific/Engineering :: Physics
Requires-Python: >=3.9
License-File: LICENSE
Requires-Dist: numpy>=1.23
Requires-Dist: scipy>=1.10
Requires-Dist: mpmath>=1.3.0
Requires-Dist: matplotlib>=3.7
Provides-Extra: dev
Requires-Dist: pytest>=7.0; extra == "dev"
Requires-Dist: build>=1.0; extra == "dev"
Requires-Dist: twine>=4.0; extra == "dev"
Requires-Dist: ruff>=0.5.0; extra == "dev"
Requires-Dist: black>=24.0; extra == "dev"
Dynamic: license-file
